tensorgenerator/__init__.py
tensorgenerator/shell/__init__.py
tensorgenerator/shell/usage.py
tensorgenerator/tensorsummary/__init__.py
tensorgenerator/tensorsummary/tensorsummary.py
tensorgenerator/torchsummary/__init__.py
tensorgenerator/torchsummary/torchsumary.py
tensorgenerator-0.2.0.dist-info/LICENSE
tensorgenerator-0.2.0.dist-info/METADATA
tensorgenerator-0.2.0.dist-info/WHEEL
tensorgenerator-0.2.0.dist-info/entry_points.txt
tensorgenerator-0.2.0.dist-info/top_level.txt
tensorgenerator-0.2.0.dist-info/zip-safe
tensorgenerator-0.2.0.dist-info/RECORD
