Metadata-Version: 2.1
Name: tensorgenerator
Version: 0.2.0
Summary: Some tools about telecom.
Home-page: https://3tel.net
Author: 3tel.net
Author-email: 3telnet@gmail.com
License: MIT License
Classifier: Programming Language :: Python :: 3
Classifier: License :: OSI Approved :: MIT License
Classifier: Operating System :: OS Independent
Requires-Python: >=3.6
License-File: LICENSE
